agixt/Agent.py
agixt/ApiClient.py
agixt/Chain.py
agixt/Complexity.py
agixt/Conversations.py
agixt/DB.py
agixt/Extensions.py
agixt/ExtensionsHub.py
agixt/Globals.py
agixt/Interactions.py
agixt/InternalClient.py
agixt/MachineState.py
agixt/MagicalAuth.py
agixt/Memories.py
agixt/Models.py
agixt/Prompts.py
agixt/Providers.py
agixt/ResponseCache.py
agixt/SeedImports.py
agixt/SharedCache.py
agixt/Task.py
agixt/TaskMonitor.py
agixt/TrialService.py
agixt/Tuning.py
agixt/WebhookManager.py
agixt/Websearch.py
agixt/WorkerRegistry.py
agixt/Workspaces.py
agixt/XT.py
agixt/__init__.py
agixt/app.py
agixt/cli.py
agixt/logging_config.py
agixt/mcp_client.py
agixt/middleware.py
agixt/run-local.py
agixt/session_tracker.py
agixt/payments/__init__.py
agixt/payments/crypto.py
agixt/payments/pricing.py
agixt/payments/stripe_service.py
agixt-1.9.0.dist-info/licenses/LICENSE
agixt-1.9.0.dist-info/METADATA
agixt-1.9.0.dist-info/WHEEL
agixt-1.9.0.dist-info/entry_points.txt
agixt-1.9.0.dist-info/top_level.txt
agixt-1.9.0.dist-info/RECORD
