Metadata-Version: 2.4
Name: agixt
Version: 1.9.0
Summary: An Artificial Intelligence Automation Platform. AI Instruction management from various providers, has an adaptive memory, and a versatile plugin system with many commands including web browsing. Supports many AI providers and models and growing support every day.
Author: Josh XT
Author-email: josh@devxt.com
Requires-Python: >=3.10
License-File: LICENSE
Requires-Dist: beautifulsoup4==4.12.3
Requires-Dist: docker==6.1.3
Requires-Dist: docx2txt==0.8
Requires-Dist: GitPython==3.1.43
Requires-Dist: pdfplumber==0.11.4
Requires-Dist: playwright==1.47.0
Requires-Dist: pandas==2.1.4
Requires-Dist: PyYAML==6.0.2
Requires-Dist: requests==2.31.0
Requires-Dist: python-dotenv==1.0.1
Requires-Dist: ffmpeg-python==0.2.0
Requires-Dist: cryptography==44.0.1
Requires-Dist: pillow==10.4.0
Requires-Dist: SQLAlchemy==2.0.34
Requires-Dist: psycopg2-binary==2.9.9
Requires-Dist: gTTS==2.5.3
Requires-Dist: tiktoken==0.7.0
Requires-Dist: PyJWT==2.9.0
Requires-Dist: websocket-client==1.8.0
Requires-Dist: lxml==5.3.0
Requires-Dist: psutil==6.0.0
Requires-Dist: sendgrid==6.11.0
Requires-Dist: httpx==0.27.2
Requires-Dist: numpy==1.26.4
Requires-Dist: mysql-connector-python==9.1.0
Requires-Dist: pydub==0.25.1
Requires-Dist: python-pptx==0.6.23
Requires-Dist: pdf2image==1.17.0
Requires-Dist: agixtsdk==0.0.80
Requires-Dist: safeexecute==0.0.22
Requires-Dist: google-generativeai==0.7.2
Requires-Dist: anthropic==0.34.2
Requires-Dist: arxiv==1.4.8
Requires-Dist: PyGithub==2.4.0
Requires-Dist: openai==1.44.0
Requires-Dist: azure-ai-inference
Requires-Dist: fastapi
Requires-Dist: uvicorn
Requires-Dist: ngrok==1.4.0
Requires-Dist: youtube-transcript-api==0.6.2
Requires-Dist: stripe==10.10.0
Requires-Dist: google-auth==2.34.0
Requires-Dist: google-api-python-client==2.144.0
Requires-Dist: google-auth-oauthlib
Requires-Dist: python-multipart==0.0.19
Requires-Dist: nest_asyncio
Requires-Dist: pyotp
Requires-Dist: pytz
Requires-Dist: openpyxl==3.1.5
Requires-Dist: platformdirs
Requires-Dist: soundfile
Requires-Dist: nbformat
Requires-Dist: opencv-python
Requires-Dist: pyzbar
Requires-Dist: pytesseract
Requires-Dist: black
Requires-Dist: fasteners
Requires-Dist: apache-libcloud
Requires-Dist: watchdog
Requires-Dist: strawberry-graphql[fastapi]
Requires-Dist: broadcaster
Requires-Dist: gql
Requires-Dist: solana
Requires-Dist: base58
Requires-Dist: solders
Requires-Dist: requests-oauthlib
Requires-Dist: blinkpy>=0.23.0
Requires-Dist: ring_doorbell>=0.9.13
Requires-Dist: aiohttp
Requires-Dist: hikvisionapi>=0.3.2
Requires-Dist: djitellopy
Requires-Dist: axis
Requires-Dist: google-ads
Requires-Dist: PyNaCl>=1.5.0
Requires-Dist: eth-account>=0.13.0
Requires-Dist: twilio
Requires-Dist: redis>=5.0.0
Requires-Dist: spacy==3.8.7
Requires-Dist: spacy-legacy==3.0.12
Requires-Dist: spacy-loggers==1.0.5
Dynamic: author
Dynamic: author-email
Dynamic: description
Dynamic: description-content-type
Dynamic: license-file
Dynamic: requires-dist
Dynamic: requires-python
Dynamic: summary
